pycallrail/__init__.py
pycallrail/base.py
pycallrail/callrail.py
pycallrail/errors.py
pycallrail/helpers.py
pycallrail/mixins.py
pycallrail/objects/__init__.py
pycallrail/objects/accounts.py
pycallrail/objects/calls.py
pycallrail/objects/companies.py
pycallrail/objects/form_submissions.py
pycallrail/objects/tags.py
pycallrail/objects/textmessages.py
tests/__init__.py
tests/cfg.py
tests/test_account.py
tests/test_apiclient.py
tests/test_call.py
tests/test_companies.py
tests/test_formsubmissions.py
tests/test_helpers.py
tests/test_integration.py
tests/test_tags.py
tests/test_textmessages.py
pycallrail-0.9.0.2.dist-info/LICENSE
pycallrail-0.9.0.2.dist-info/METADATA
pycallrail-0.9.0.2.dist-info/WHEEL
pycallrail-0.9.0.2.dist-info/top_level.txt
pycallrail-0.9.0.2.dist-info/RECORD
