Metadata-Version: 2.1
Name: pycallrail
Version: 0.9.0.2
Summary: An unofficial Python wrapper for the CallRail API
Home-page: https://github.com/predictive-data-lab/pycallrail
Author: Engineering @ Predictive Data Lab
License: MIT
Project-URL: Documentation, https://pycallrail.readthedocs.io/en/latest/
Project-URL: Issue Tracker, https://github.com/predictive-data-lab/pycallrail/issues
Classifier: Development Status :: 5 - Production/Stable
Classifier: License :: OSI Approved :: MIT License
Classifier: Intended Audience :: Developers
Classifier: Natural Language :: English
Classifier: Operating System :: OS Independent
Classifier: Programming Language :: Python
Classifier: Topic :: Software Development :: Libraries :: Python Modules
Classifier: Topic :: Utilities
Classifier: Topic :: Internet :: WWW/HTTP :: Dynamic Content
Classifier: Topic :: Communications
Requires-Python: >=3.8.0
License-File: LICENSE
Requires-Dist: ujson (~=5.7.0)
Requires-Dist: aiohttp (~=3.8.4)
Requires-Dist: python-dateutil
Requires-Dist: typeguard
Requires-Dist: typing-extensions
Provides-Extra: docs
Requires-Dist: sphinx (==4.4.0) ; extra == 'docs'
Requires-Dist: sphinxcontrib-trio ; extra == 'docs'
Requires-Dist: sphinxcontrib-websupport ; extra == 'docs'
Requires-Dist: typing-extensions (>=4.3.0) ; extra == 'docs'
Provides-Extra: test
Requires-Dist: coverage[toml] ; extra == 'test'
Requires-Dist: pytest ; extra == 'test'
Requires-Dist: pytest-mock ; extra == 'test'
Requires-Dist: pytest-cov ; extra == 'test'
Requires-Dist: typing-extensions (>=4.3.0) ; extra == 'test'
Requires-Dist: requests-mock ; extra == 'test'
Requires-Dist: typeguard ; extra == 'test'
Requires-Dist: python-dateutil ; extra == 'test'
